peth/__init__.py
peth/cli.py
peth/console.py
peth/core/__init__.py
peth/core/analysis.py
peth/core/config.py
peth/core/log.py
peth/core/peth.py
peth/core/tracer/__init__.py
peth/core/tracer/js/event_tracer.js
peth/core/tracer/js/geth_tracer.js
peth/core/tracer/js/legacy_tracer.js
peth/core/tracer/js/test_tracer.js
peth/core/tracer/tracer.py
peth/core/tracer/txtrace.py
peth/core/tracer/utils.py
peth/data/bytecode/ExecTxWrapper.json
peth/data/bytecode/GetBalanceWrapper.json
peth/data/bytecode/MockSender.json
peth/data/bytecode/MockSender.sol
peth/data/chains.yaml
peth/data/config.ini
peth/data/contracts.yaml
peth/data/tokens/arb.json
peth/data/tokens/avax.json
peth/data/tokens/base.json
peth/data/tokens/bsc.json
peth/data/tokens/eth.json
peth/data/tokens/ftm.json
peth/data/tokens/matic.json
peth/data/tokens/op.json
peth/data/tokens.yaml
peth/eth/__init__.py
peth/eth/abi/__init__.py
peth/eth/abi/abi.py
peth/eth/abi/abifunc.py
peth/eth/abi/abitype.py
peth/eth/abi/utils.py
peth/eth/bytecode.py
peth/eth/contract.py
peth/eth/evm/__init__.py
peth/eth/evm/chain.py
peth/eth/evm/contract.py
peth/eth/evm/exceptions.py
peth/eth/evm/forkchain.py
peth/eth/evm/inspector.py
peth/eth/evm/receipt.py
peth/eth/evm/trace.py
peth/eth/evm/transaction.py
peth/eth/evm/utils.py
peth/eth/evm/vm.py
peth/eth/opcodes.py
peth/eth/scan.py
peth/eth/sigs.py
peth/eth/utils.py
peth/eth/web3ex.py
peth/util/__init__.py
peth/util/diff.py
peth/util/graph.py
peth/util/logos.py
peth/util/markdown.py
peth/util/slither.py
peth/util/solc.py
peth/util/source.py
peth-1.0.10.dist-info/LICENSE
peth-1.0.10.dist-info/METADATA
peth-1.0.10.dist-info/WHEEL
peth-1.0.10.dist-info/entry_points.txt
peth-1.0.10.dist-info/RECORD
