Metadata-Version: 2.1
Name: peth
Version: 1.0.10
Summary: An all-in-one Ethereum SDK and command-line tool written in python.
Home-page: https://github.com/lmy375/peth/
License: AGPL-3.0
Author: Moon
Author-email: lmy375@139.com
Requires-Python: >=3.10,<4.0
Classifier: License :: OSI Approved :: GNU Affero General Public License v3
Classifier: Programming Language :: Python :: 3
Classifier: Programming Language :: Python :: 3.10
Classifier: Programming Language :: Python :: 3.11
Classifier: Programming Language :: Python :: 3.12
Requires-Dist: py-solc-x (>=1.1.1,<2.0.0)
Requires-Dist: pyyaml (>=6.0.0,<7.0.0)
Requires-Dist: requests (>=2.28.0,<3.0.0)
Requires-Dist: web3 (>=6.20.0,<7.0.0)
Project-URL: Documentation, https://peth.readthedocs.io/
Project-URL: Repository, https://github.com/lmy375/peth/
